cargo/__init__.py
cargo/clients.py
cargo/cursors.py
cargo/exceptions.py
cargo/expressions.py
cargo/orm.py
cargo/relationships.py
cargo/statements.py
cargo/validators.py
cargo/builder/__init__.py
cargo/builder/casts.py
cargo/builder/comments.py
cargo/builder/create_shortcuts.py
cargo/builder/databases.py
cargo/builder/domains.py
cargo/builder/drop_shortcuts.py
cargo/builder/extensions.py
cargo/builder/extras.py
cargo/builder/fields.py
cargo/builder/foreign_keys.py
cargo/builder/functions.py
cargo/builder/indexes.py
cargo/builder/operators.py
cargo/builder/roles.py
cargo/builder/rules.py
cargo/builder/schemas.py
cargo/builder/sequences.py
cargo/builder/tables.py
cargo/builder/tablespaces.py
cargo/builder/triggers.py
cargo/builder/types.py
cargo/builder/utils.py
cargo/builder/views.py
cargo/etc/__init__.py
cargo/etc/operators.py
cargo/etc/passwords.py
cargo/etc/types.py
cargo/etc/usernames.py
cargo/etc/translator/__init__.py
cargo/etc/translator/postgres.py
cargo/fields/__init__.py
cargo/fields/binary.py
cargo/fields/bit.py
cargo/fields/boolean.py
cargo/fields/character.py
cargo/fields/datetimes.py
cargo/fields/encrypted.py
cargo/fields/extras.py
cargo/fields/field.py
cargo/fields/geometry.py
cargo/fields/identifier.py
cargo/fields/integer.py
cargo/fields/keyvalue.py
cargo/fields/networking.py
cargo/fields/numeric.py
cargo/fields/ranges.py
cargo/fields/sequence.py
cargo/logic/__init__.py
cargo/logic/binary.py
cargo/logic/bit.py
cargo/logic/datetimes.py
cargo/logic/geometry.py
cargo/logic/keyvalue.py
cargo/logic/networking.py
cargo/logic/ranges.py
cargo/logic/sequence.py
cargo_orm-0.2.2.dist-info/LICENSE
cargo_orm-0.2.2.dist-info/METADATA
cargo_orm-0.2.2.dist-info/WHEEL
cargo_orm-0.2.2.dist-info/top_level.txt
cargo_orm-0.2.2.dist-info/RECORD
