Metadata-Version: 2.1
Name: cargo-orm
Version: 0.2.2
Summary: A friendly, rich Postgres ORM for Python 3.5+.
Home-page: https://github.com/jaredlunde/cargo-orm
Author: Jared Lunde
Author-email: jared@tessellate.io
License: MIT
Platform: UNKNOWN
Classifier: Development Status :: 4 - Beta
Classifier: License :: OSI Approved :: MIT License
Classifier: Programming Language :: Python :: 3
Classifier: Programming Language :: Python :: Implementation :: CPython
Classifier: Topic :: Database :: Front-Ends
Classifier: Operating System :: OS Independent
Requires-Dist: argon2-cffi
Requires-Dist: arrow
Requires-Dist: babel
Requires-Dist: bcrypt
Requires-Dist: bitstring
Requires-Dist: cnamedtuple
Requires-Dist: humanize
Requires-Dist: netaddr
Requires-Dist: python-dateutil
Requires-Dist: passlib
Requires-Dist: psycopg2
Requires-Dist: pycrypto
Requires-Dist: python-slugify
Requires-Dist: sqlparse
Requires-Dist: vital-tools
Requires-Dist: yapf
